dragn/__init__.py
dragn/dice/__init__.py
dragn/dice/die.py
dragn/dice/tumbler.py
dragn/tests/__init__.py
dragn/tests/test_dice.py
dragn-0.4.0.dist-info/LICENSE
dragn-0.4.0.dist-info/METADATA
dragn-0.4.0.dist-info/WHEEL
dragn-0.4.0.dist-info/top_level.txt
dragn-0.4.0.dist-info/RECORD
