Metadata-Version: 2.1
Name: dragn
Version: 0.4.0
Summary: A library to emulate rolling dice
Home-page: https://github.com/lurst/dragn
Author: Gil Goncalves
Author-email: lursty@gmail.com
License: UNKNOWN
Platform: UNKNOWN
Classifier: Development Status :: 4 - Beta
Classifier: Intended Audience :: Developers
Classifier: License :: OSI Approved :: MIT License
Classifier: Operating System :: OS Independent
Classifier: Programming Language :: Python
Classifier: Programming Language :: Python :: 3.7
Classifier: Programming Language :: Python :: 3 :: Only
